{
  "cache_invalidated_at": "2026-06-29T11:50:48.477306Z",
  "description": null,
  "archived": false,
  "view_count": 0,
  "collection_position": null,
  "source_card_id": null,
  "table_id": null,
  "can_run_adhoc_query": true,
  "result_metadata": [
    {
      "name": "period",
      "database_type": "text",
      "base_type": "type/Text",
      "display_name": "period",
      "field_ref": [
        "field",
        "period",
        {
          "base-type": "type/Text"
        }
      ]
    },
    {
      "name": "project_name",
      "database_type": "varchar",
      "base_type": "type/Text",
      "display_name": "project_name",
      "field_ref": [
        "field",
        "project_name",
        {
          "base-type": "type/Text"
        }
      ]
    },
    {
      "name": "customer",
      "database_type": "text",
      "base_type": "type/Text",
      "display_name": "customer",
      "field_ref": [
        "field",
        "customer",
        {
          "base-type": "type/Text"
        }
      ]
    },
    {
      "name": "base_effort",
      "database_type": "numeric",
      "base_type": "type/Decimal",
      "display_name": "base_effort",
      "field_ref": [
        "field",
        "base_effort",
        {
          "base-type": "type/Decimal"
        }
      ]
    },
    {
      "name": "team_effort",
      "database_type": "numeric",
      "base_type": "type/Decimal",
      "display_name": "team_effort",
      "field_ref": [
        "field",
        "team_effort",
        {
          "base-type": "type/Decimal"
        }
      ]
    },
    {
      "name": "tribe_effort",
      "database_type": "numeric",
      "base_type": "type/Decimal",
      "display_name": "tribe_effort",
      "field_ref": [
        "field",
        "tribe_effort",
        {
          "base-type": "type/Decimal"
        }
      ]
    },
    {
      "name": "final_effort",
      "database_type": "numeric",
      "base_type": "type/Decimal",
      "display_name": "final_effort",
      "field_ref": [
        "field",
        "final_effort",
        {
          "base-type": "type/Decimal"
        }
      ]
    },
    {
      "name": "distributed_effort",
      "database_type": "numeric",
      "base_type": "type/Decimal",
      "display_name": "distributed_effort",
      "field_ref": [
        "field",
        "distributed_effort",
        {
          "base-type": "type/Decimal"
        }
      ]
    },
    {
      "name": "capex_effort",
      "database_type": "numeric",
      "base_type": "type/Decimal",
      "display_name": "capex_effort",
      "field_ref": [
        "field",
        "capex_effort",
        {
          "base-type": "type/Decimal"
        }
      ]
    },
    {
      "name": "opex_effort",
      "database_type": "numeric",
      "base_type": "type/Decimal",
      "display_name": "opex_effort",
      "field_ref": [
        "field",
        "opex_effort",
        {
          "base-type": "type/Decimal"
        }
      ]
    }
  ],
  "embedding_type": null,
  "creator": {
    "email": "admin@jppm.local",
    "first_name": "Admin",
    "is_data_analyst": false,
    "last_login": "2026-06-29T13:17:21.623294Z",
    "is_qbnewb": false,
    "is_superuser": true,
    "id": 1,
    "last_name": "PPM",
    "tenant_id": null,
    "date_joined": "2026-06-29T08:21:32.398523Z",
    "common_name": "Admin PPM"
  },
  "initially_published_at": null,
  "can_write": true,
  "card_schema": 23,
  "database_id": 2,
  "enable_embedding": false,
  "collection_id": 31,
  "query_type": "native",
  "name": "Distribution Detail",
  "last_query_start": null,
  "is_remote_synced": false,
  "dashboard_count": 1,
  "document_id": null,
  "last_used_at": "2026-06-29T11:38:39.807668Z",
  "dashboard": null,
  "type": "question",
  "dimensions": null,
  "average_query_time": null,
  "creator_id": 1,
  "can_restore": false,
  "moderation_reviews": [],
  "updated_at": "2026-06-29T11:50:48.474076Z",
  "made_public_by_id": null,
  "embedding_params": null,
  "cache_ttl": null,
  "dataset_query": {
    "lib/type": "mbql/query",
    "database": 2,
    "stages": [
      {
        "native": "SELECT period, project_name, customer,\n  ROUND(logged_time_person_day::numeric,2) AS base_effort,\n  ROUND(team_effort::numeric,2) AS team_effort,\n  ROUND(tribe_effort::numeric,2) AS tribe_effort,\n  ROUND(final_effort::numeric,2) AS final_effort,\n  ROUND(total_distributed_all::numeric,2) AS distributed_effort,\n  ROUND(final_effort_capex::numeric,2) AS capex_effort,\n  ROUND(final_effort_opex::numeric,2) AS opex_effort\nFROM mart.fact_financial_dashboard_2026\n\nWHERE 1=1\n  [[AND period = {{period_filter}}]]\n\n  [[AND project_name = {{project_key}}]]\n\n  [[AND team = {{team}}]]\nORDER BY period DESC, final_effort DESC\nLIMIT 500",
        "lib/type": "mbql.stage/native",
        "template-tags": {
          "period_filter": {
            "display-name": "Period",
            "type": "text",
            "id": "33333333-3333-3333-3333-333333333333",
            "name": "period_filter",
            "required": false
          },
          "project_key": {
            "display-name": "Project",
            "type": "text",
            "id": "44444444-4444-4444-4444-444444444444",
            "name": "project_key",
            "required": false
          },
          "team": {
            "display-name": "Team",
            "type": "text",
            "id": "55555555-5555-5555-5555-555555555555",
            "name": "team",
            "required": false
          }
        }
      }
    ]
  },
  "dimension_mappings": null,
  "id": 208,
  "legacy_query": null,
  "parameter_mappings": [],
  "can_manage_db": true,
  "display": "table",
  "archived_directly": false,
  "entity_id": "XFh_p6nFlFf2-mgjvJNwD",
  "param_fields": {},
  "collection_preview": true,
  "last-edit-info": {
    "id": 1,
    "email": "admin@jppm.local",
    "first_name": "Admin",
    "last_name": "PPM",
    "timestamp": "2026-06-29T11:50:48.499201Z"
  },
  "visualization_settings": {},
  "collection": {
    "authority_level": null,
    "description": null,
    "archived": false,
    "slug": "financial",
    "archive_operation_id": null,
    "name": "Financial",
    "is_remote_synced": false,
    "personal_owner_id": null,
    "type": null,
    "is_sample": false,
    "id": 31,
    "archived_directly": null,
    "entity_id": "vPVIrWdOjwKTJb_XWASDK",
    "location": "/25/",
    "namespace": null,
    "is_personal": false,
    "created_at": "2026-06-29T11:38:16.148295Z"
  },
  "metabase_version": "v0.62.3.3 (686cac9)",
  "parameters": [],
  "dashboard_id": null,
  "created_at": "2026-06-29T11:38:39.807668Z",
  "parameter_usage_count": 0,
  "public_uuid": null,
  "can_delete": false
}